learning/__init__.py
learning/matrix_factorization.py
learning/non_negative_matrix_factorization.py
learning-0.0.dev0.dist-info/METADATA
learning-0.0.dev0.dist-info/RECORD
learning-0.0.dev0.dist-info/WHEEL
learning-0.0.dev0.dist-info/top_level.txt
