Metadata-Version: 1.2
Name: learning
Version: 0.0.dev0
Summary: For data-intern
Home-page: https://github.com/kwacgit/myRecommendationSystem
Author: Kazuya Nishi
Author-email: nishi.k.mllab.nit@gmail.com
Maintainer: Kazuya Nishi
Maintainer-email: nishi.k.mllab.nit@gmail.com
License: MIT
Platform: UNKNOWN
Classifier: License :: OSI Approved :: MIT License
